{
    "buildBehavior": {
        "type": "sync"
    },
    "columns": [
        {
            "hidden": false,
            "id": "LFBI_ID",
            "indexed": false,
            "isUpsertBy": false,
            "name": "LFBI_ID",
            "oid": "f4446302-25af-40ba-8a85-af5cb593603b",
            "precision": 10,
            "scale": 0,
            "size": 4,
            "type": 8
        },
        {
            "hidden": false,
            "id": "LFBI_LoadTime",
            "indexed": false,
            "isUpsertBy": false,
            "name": "LFBI_LoadTime",
            "oid": "b679c689-c471-4106-9d5d-7c7eedf17ffe",
            "precision": 0,
            "scale": 0,
            "size": 8,
            "type": 33
        },
        {
            "hidden": false,
            "id": "FullDate",
            "indexed": false,
            "isUpsertBy": false,
            "name": "FullDate",
            "oid": "f21182aa-3209-4727-aac0-535ac9e53460",
            "precision": 0,
            "scale": 0,
            "size": 8,
            "type": 33
        },
        {
            "hidden": false,
            "id": "Year",
            "indexed": false,
            "isUpsertBy": false,
            "name": "Year",
            "oid": "208e9d4c-6ea5-40dd-ba79-2f031a9f0c58",
            "precision": 10,
            "scale": 0,
            "size": 4,
            "type": 8
        },
        {
            "hidden": false,
            "id": "Quarter",
            "indexed": true,
            "isUpsertBy": false,
            "name": "Quarter",
            "oid": "042087b0-b3e0-4077-a231-d26caf8479c3",
            "precision": 0,
            "scale": 0,
            "size": 65536,
            "type": 12
        },
        {
            "hidden": false,
            "id": "Quarter of Year",
            "indexed": false,
            "isUpsertBy": false,
            "name": "Quarter of Year",
            "oid": "c23db64d-cc1e-4582-9d4b-ff6ec28ebca9",
            "precision": 10,
            "scale": 0,
            "size": 4,
            "type": 8
        },
        {
            "hidden": false,
            "id": "Month",
            "indexed": true,
            "isUpsertBy": false,
            "name": "Month",
            "oid": "e360724c-bedf-44d9-97ac-548457019d9d",
            "precision": 0,
            "scale": 0,
            "size": 65536,
            "type": 12
        },
        {
            "hidden": false,
            "id": "Month of Year",
            "indexed": false,
            "isUpsertBy": false,
            "name": "Month of Year",
            "oid": "0cea4c5e-bf9f-4079-a024-1a579c0ebdc7",
            "precision": 10,
            "scale": 0,
            "size": 4,
            "type": 8
        },
        {
            "hidden": false,
            "id": "Week",
            "indexed": true,
            "isUpsertBy": false,
            "name": "Week",
            "oid": "f577b225-733d-4263-a9ba-f67ef0eff477",
            "precision": 0,
            "scale": 0,
            "size": 65536,
            "type": 12
        },
        {
            "hidden": false,
            "id": "Week of Year",
            "indexed": false,
            "isUpsertBy": false,
            "name": "Week of Year",
            "oid": "f9d8ee92-3945-4ee6-8826-4f72cce01096",
            "precision": 10,
            "scale": 0,
            "size": 4,
            "type": 8
        },
        {
            "hidden": false,
            "id": "Day",
            "indexed": true,
            "isUpsertBy": false,
            "name": "Day",
            "oid": "90f35251-c2e9-494c-95d7-1f3a4a3ccd75",
            "precision": 0,
            "scale": 0,
            "size": 65536,
            "type": 12
        },
        {
            "hidden": false,
            "id": "Day of Week",
            "indexed": false,
            "isUpsertBy": false,
            "name": "Day of Week",
            "oid": "611118e9-3639-4064-b5d7-026c909295b0",
            "precision": 10,
            "scale": 0,
            "size": 4,
            "type": 8
        },
        {
            "hidden": false,
            "id": "Day of Month",
            "indexed": false,
            "isUpsertBy": false,
            "name": "Day of Month",
            "oid": "879f6b1e-193a-467a-84eb-c0cd68b0e725",
            "precision": 10,
            "scale": 0,
            "size": 4,
            "type": 8
        },
        {
            "hidden": false,
            "id": "Day of Year",
            "indexed": false,
            "isUpsertBy": false,
            "name": "Day of Year",
            "oid": "e46eae9b-92f2-4bd6-92c6-c8275d0b9d86",
            "precision": 10,
            "scale": 0,
            "size": 4,
            "type": 8
        }
    ],
    "configOptions": {
    },
    "dataset": "843828ae-3db0-44bf-8ec9-fe043c4993b7",
    "hidden": false,
    "id": "d_PolicyCancellationDate",
    "isMaterialized": false,
    "name": "dw.d_PolicyCancellationDate",
    "oid": "313fb969-e3cd-4beb-a43e-bcb1d0035f2a",
    "tupleTransformations": [
    ],
    "type": "base"
}
