{
    "buildBehavior": {
        "type": "sync"
    },
    "columns": [
        {
            "hidden": false,
            "id": "LFBI_ID",
            "indexed": false,
            "isUpsertBy": false,
            "name": "LFBI_ID",
            "oid": "4fafe7ad-5a74-405f-8917-01042d89afa7",
            "precision": 10,
            "scale": 0,
            "size": 4,
            "type": 8
        },
        {
            "hidden": false,
            "id": "LFBI_LoadTime",
            "indexed": false,
            "isUpsertBy": false,
            "name": "LFBI_LoadTime",
            "oid": "81f9cafb-7b73-495d-9392-a0b272a79653",
            "precision": 0,
            "scale": 0,
            "size": 8,
            "type": 33
        },
        {
            "hidden": false,
            "id": "LFBI_Start",
            "indexed": false,
            "isUpsertBy": false,
            "name": "LFBI_Start",
            "oid": "9c9ade90-5eb2-4dc8-80fe-b07a66cb8636",
            "precision": 0,
            "scale": 0,
            "size": 8,
            "type": 33
        },
        {
            "hidden": false,
            "id": "LFBI_End",
            "indexed": false,
            "isUpsertBy": false,
            "name": "LFBI_End",
            "oid": "c0edc605-bc5a-4b2d-9e47-9f93427e30e3",
            "precision": 0,
            "scale": 0,
            "size": 8,
            "type": 33
        },
        {
            "hidden": false,
            "id": "LFBI_Current",
            "indexed": false,
            "isUpsertBy": false,
            "name": "LFBI_Current",
            "oid": "c048cb2c-5933-443c-8779-adb7a0acbe0c",
            "precision": 0,
            "scale": 0,
            "size": 65536,
            "type": 2
        },
        {
            "hidden": false,
            "id": "LiabilityExposuresID",
            "indexed": false,
            "isUpsertBy": false,
            "name": "LiabilityExposuresID",
            "oid": "0ffa6797-bd83-4aab-8af2-8bc7397af143",
            "precision": 10,
            "scale": 0,
            "size": 4,
            "type": 8
        },
        {
            "hidden": false,
            "id": "LocationID",
            "indexed": false,
            "isUpsertBy": false,
            "name": "LocationID",
            "oid": "31cb935c-4cb1-41e6-9872-41976cc9e904",
            "precision": 10,
            "scale": 0,
            "size": 4,
            "type": 8
        },
        {
            "hidden": false,
            "id": "SourceID",
            "indexed": false,
            "isUpsertBy": false,
            "name": "SourceID",
            "oid": "7cbcd312-fe9f-4c88-9ff7-f8278b78e865",
            "precision": 10,
            "scale": 0,
            "size": 4,
            "type": 8
        },
        {
            "hidden": false,
            "id": "SubLOB",
            "indexed": true,
            "isUpsertBy": false,
            "name": "SubLOB",
            "oid": "5deb8056-2739-4f2e-8864-f4f25c7bf987",
            "precision": 0,
            "scale": 0,
            "size": 4,
            "type": 22
        },
        {
            "hidden": false,
            "id": "Transaction",
            "indexed": true,
            "isUpsertBy": false,
            "name": "Transaction",
            "oid": "3717e107-aad6-4ed2-9462-10e599ee16b8",
            "precision": 0,
            "scale": 0,
            "size": 65536,
            "type": 22
        },
        {
            "hidden": false,
            "id": "TransactionDate",
            "indexed": false,
            "isUpsertBy": false,
            "name": "TransactionDate",
            "oid": "8183e2dd-139c-4ed7-ac5e-26d0738e56f3",
            "precision": 0,
            "scale": 0,
            "size": 8,
            "type": 4
        },
        {
            "hidden": false,
            "id": "ClassCodeDescription",
            "indexed": true,
            "isUpsertBy": false,
            "name": "ClassCodeDescription",
            "oid": "e9e4e1fb-2ea6-4659-a4bd-5bf3ba44ea2b",
            "precision": 0,
            "scale": 0,
            "size": 65536,
            "type": 22
        },
        {
            "hidden": false,
            "id": "ClassCode",
            "indexed": true,
            "isUpsertBy": false,
            "name": "ClassCode",
            "oid": "75611cb2-bd1f-4e04-afcb-0783fd80e1e0",
            "precision": 0,
            "scale": 0,
            "size": 65536,
            "type": 22
        },
        {
            "hidden": false,
            "id": "QCClassCode",
            "indexed": false,
            "isUpsertBy": false,
            "name": "QCClassCode",
            "oid": "19ad9872-4017-4504-9534-342e5227bfbc",
            "precision": 10,
            "scale": 0,
            "size": 4,
            "type": 8
        },
        {
            "hidden": false,
            "id": "SIC",
            "indexed": true,
            "isUpsertBy": false,
            "name": "SIC",
            "oid": "bd91dbf1-a2e6-4e1b-93d8-cc99d1cb154e",
            "precision": 0,
            "scale": 0,
            "size": 65536,
            "type": 22
        },
        {
            "hidden": false,
            "id": "Occupancy",
            "indexed": true,
            "isUpsertBy": false,
            "name": "Occupancy",
            "oid": "de6f1601-f76f-4ef9-9195-ccf5593862e0",
            "precision": 0,
            "scale": 0,
            "size": 65536,
            "type": 22
        },
        {
            "hidden": false,
            "id": "ILFTable",
            "indexed": true,
            "isUpsertBy": false,
            "name": "ILFTable",
            "oid": "0d9ed8e7-1e66-4fc0-9309-3a69519b4dad",
            "precision": 0,
            "scale": 0,
            "size": 65536,
            "type": 22
        },
        {
            "hidden": false,
            "id": "ExcludeProducts",
            "indexed": false,
            "isUpsertBy": false,
            "name": "ExcludeProducts",
            "oid": "87345a86-f0e2-4edd-bb16-074204e4e226",
            "precision": 0,
            "scale": 0,
            "size": 65536,
            "type": 2
        },
        {
            "hidden": false,
            "id": "ExposureBasis",
            "indexed": true,
            "isUpsertBy": false,
            "name": "ExposureBasis",
            "oid": "dadd523d-20e3-4021-a891-a8e8fbbd8dbc",
            "precision": 0,
            "scale": 0,
            "size": 65536,
            "type": 22
        },
        {
            "hidden": false,
            "id": "Exposure",
            "indexed": true,
            "isUpsertBy": false,
            "name": "Exposure",
            "oid": "de9e7cc8-65d2-418b-92ee-0cc90c5fe21c",
            "precision": 0,
            "scale": 0,
            "size": 65536,
            "type": 22
        },
        {
            "hidden": false,
            "id": "PremisesA",
            "indexed": true,
            "isUpsertBy": false,
            "name": "PremisesA",
            "oid": "be1dc398-350a-4bc6-b108-4ced3565bcb2",
            "precision": 0,
            "scale": 0,
            "size": 65536,
            "type": 22
        },
        {
            "hidden": false,
            "id": "ProductsA",
            "indexed": true,
            "isUpsertBy": false,
            "name": "ProductsA",
            "oid": "cd1d769c-369d-4405-b30f-b65887522022",
            "precision": 0,
            "scale": 0,
            "size": 65536,
            "type": 22
        },
        {
            "hidden": false,
            "id": "ClassCodeDescription_Secondary",
            "indexed": true,
            "isUpsertBy": false,
            "name": "ClassCodeDescription_Secondary",
            "oid": "8ef0e6c7-4570-4b8f-ac66-c4ebba87bc4c",
            "precision": 0,
            "scale": 0,
            "size": 65536,
            "type": 22
        },
        {
            "hidden": false,
            "id": "IsLiquorClass",
            "indexed": false,
            "isUpsertBy": false,
            "name": "IsLiquorClass",
            "oid": "6a8cc022-56fb-413d-bd56-7fa4483804f0",
            "precision": 0,
            "scale": 0,
            "size": 65536,
            "type": 2
        },
        {
            "hidden": false,
            "id": "ExcludePremises",
            "indexed": false,
            "isUpsertBy": false,
            "name": "ExcludePremises",
            "oid": "8137205a-f47b-4b35-b512-b669ff7838f0",
            "precision": 0,
            "scale": 0,
            "size": 65536,
            "type": 2
        },
        {
            "hidden": false,
            "id": "CompositeRating",
            "indexed": true,
            "isUpsertBy": false,
            "name": "CompositeRating",
            "oid": "30af487d-ce2b-4468-bd5e-34a141cc7bc0",
            "precision": 0,
            "scale": 0,
            "size": 65536,
            "type": 22
        },
        {
            "hidden": false,
            "id": "Occurence_or_ClaimsMade",
            "indexed": true,
            "isUpsertBy": false,
            "name": "Occurence_or_ClaimsMade",
            "oid": "bcaabfb8-4a74-45f5-b366-068a34b67293",
            "precision": 0,
            "scale": 0,
            "size": 500,
            "type": 22
        },
        {
            "hidden": false,
            "id": "ExpenseIncluded",
            "indexed": true,
            "isUpsertBy": false,
            "name": "ExpenseIncluded",
            "oid": "77481016-25d4-468d-a63a-6f68dab94b0b",
            "precision": 0,
            "scale": 0,
            "size": 500,
            "type": 22
        },
        {
            "hidden": false,
            "id": "PerClaim_WrongfulAct",
            "indexed": true,
            "isUpsertBy": false,
            "name": "PerClaim_WrongfulAct",
            "oid": "874a0f36-32bf-480f-855c-d4be2a79c417",
            "precision": 0,
            "scale": 0,
            "size": 500,
            "type": 22
        },
        {
            "hidden": false,
            "id": "ExposureGroup",
            "indexed": true,
            "isUpsertBy": false,
            "name": "ExposureGroup",
            "oid": "30222088-d716-4033-b22b-fde68a98196b",
            "precision": 0,
            "scale": 0,
            "size": 500,
            "type": 22
        },
        {
            "hidden": false,
            "id": "PECategory",
            "indexed": true,
            "isUpsertBy": false,
            "name": "PECategory",
            "oid": "731c8015-982c-4d00-9020-d39c52da9862",
            "precision": 0,
            "scale": 0,
            "size": 500,
            "type": 22
        },
        {
            "hidden": false,
            "id": "LocationType",
            "indexed": true,
            "isUpsertBy": false,
            "name": "LocationType",
            "oid": "d48345d3-d8fe-4aa2-ab10-9b843b526697",
            "precision": 0,
            "scale": 0,
            "size": 500,
            "type": 22
        },
        {
            "hidden": false,
            "id": "Population",
            "indexed": true,
            "isUpsertBy": false,
            "name": "Population",
            "oid": "889727d7-3fa9-4ed4-bbf3-cf228a37dc5c",
            "precision": 0,
            "scale": 0,
            "size": 500,
            "type": 22
        },
        {
            "hidden": false,
            "id": "DormitoryExposure",
            "indexed": true,
            "isUpsertBy": false,
            "name": "DormitoryExposure",
            "oid": "d74478f7-7afb-4248-8dfc-5c3bb69dc91e",
            "precision": 0,
            "scale": 0,
            "size": 500,
            "type": 22
        },
        {
            "hidden": false,
            "id": "FungiBacteriaExclusion",
            "indexed": true,
            "isUpsertBy": false,
            "name": "FungiBacteriaExclusion",
            "oid": "791af10b-7986-4079-b2df-4ef7eab65919",
            "precision": 0,
            "scale": 0,
            "size": 500,
            "type": 22
        },
        {
            "hidden": false,
            "id": "PrincipalsProtectiveLiabCoverage",
            "indexed": true,
            "isUpsertBy": false,
            "name": "PrincipalsProtectiveLiabCoverage",
            "oid": "93c1f223-1f8d-4469-9c7e-98345c0ca4e1",
            "precision": 0,
            "scale": 0,
            "size": 500,
            "type": 22
        },
        {
            "hidden": false,
            "id": "ConstructionProjMgmtProtective_LiabCoverage",
            "indexed": true,
            "isUpsertBy": false,
            "name": "ConstructionProjMgmtProtective_LiabCoverage",
            "oid": "f5177c85-46a4-4bca-8142-8144701104a8",
            "precision": 0,
            "scale": 0,
            "size": 500,
            "type": 22
        },
        {
            "hidden": false,
            "id": "PartTimeorAuxiliaryReserveOfficer",
            "indexed": true,
            "isUpsertBy": false,
            "name": "PartTimeorAuxiliaryReserveOfficer",
            "oid": "bf0a9a92-9a26-447a-b2c4-5d0b125d6841",
            "precision": 0,
            "scale": 0,
            "size": 500,
            "type": 22
        },
        {
            "hidden": false,
            "id": "JailorHoldingDetentionCell",
            "indexed": true,
            "isUpsertBy": false,
            "name": "JailorHoldingDetentionCell",
            "oid": "badc750a-d201-4b53-b62f-79d35be54e8c",
            "precision": 0,
            "scale": 0,
            "size": 500,
            "type": 22
        },
        {
            "hidden": false,
            "id": "CALEAAccreditation",
            "indexed": true,
            "isUpsertBy": false,
            "name": "CALEAAccreditation",
            "oid": "8dbd54fa-3030-4efb-844b-811f26d171f5",
            "precision": 0,
            "scale": 0,
            "size": 500,
            "type": 22
        },
        {
            "hidden": false,
            "id": "LawEnforcementTelevisionNetworkSubscriber",
            "indexed": true,
            "isUpsertBy": false,
            "name": "LawEnforcementTelevisionNetworkSubscriber",
            "oid": "dda42ef1-e962-4f31-ae46-354f81187144",
            "precision": 0,
            "scale": 0,
            "size": 500,
            "type": 22
        },
        {
            "hidden": false,
            "id": "SeminarorOtherFormalTraining",
            "indexed": true,
            "isUpsertBy": false,
            "name": "SeminarorOtherFormalTraining",
            "oid": "76cfb78c-9e7e-4b54-902a-ede1eba7b37f",
            "precision": 0,
            "scale": 0,
            "size": 500,
            "type": 22
        },
        {
            "hidden": false,
            "id": "WaterSewerUtility",
            "indexed": true,
            "isUpsertBy": false,
            "name": "WaterSewerUtility",
            "oid": "69f11c11-7fc4-4d0a-8116-eb473900960e",
            "precision": 0,
            "scale": 0,
            "size": 500,
            "type": 22
        },
        {
            "hidden": false,
            "id": "DoesEPLApply",
            "indexed": true,
            "isUpsertBy": false,
            "name": "DoesEPLApply",
            "oid": "702f43a0-8618-462c-a454-735f267b595a",
            "precision": 0,
            "scale": 0,
            "size": 500,
            "type": 22
        },
        {
            "hidden": false,
            "id": "ExposureKey",
            "indexed": true,
            "isUpsertBy": false,
            "name": "ExposureKey",
            "oid": "df3e7901-e5f2-4c8f-8918-6327e645e076",
            "precision": 0,
            "scale": 0,
            "size": 163,
            "type": 22
        },
        {
            "hidden": false,
            "id": "ExposureNumber",
            "indexed": false,
            "isUpsertBy": false,
            "name": "ExposureNumber",
            "oid": "67dc6247-c701-4096-83e1-16b981b54e0a",
            "precision": 19,
            "scale": 0,
            "size": 8,
            "type": 0
        }
    ],
    "configOptions": {
    },
    "dataset": "843828ae-3db0-44bf-8ec9-fe043c4993b7",
    "hidden": false,
    "id": "d_ExposureGeneralLiability",
    "isMaterialized": false,
    "name": "dw.d_ExposureGeneralLiability",
    "oid": "9626e928-ff22-4c68-a7a2-4cfa6959cc20",
    "tupleTransformations": [
    ],
    "type": "base"
}
